tidesurf/__init__.py
tidesurf/counter.c
tidesurf/counter.cpython-310-x86_64-linux-gnu.so
tidesurf/counter.pxd
tidesurf/counter.py
tidesurf/enums.c
tidesurf/enums.cpython-310-x86_64-linux-gnu.so
tidesurf/enums.pxd
tidesurf/enums.pyx
tidesurf/main.c
tidesurf/main.cpython-310-x86_64-linux-gnu.so
tidesurf/main.py
tidesurf/transcript.c
tidesurf/transcript.cpython-310-x86_64-linux-gnu.so
tidesurf/transcript.pxd
tidesurf/transcript.py
tidesurf-0.2.1.dist-info/METADATA
tidesurf-0.2.1.dist-info/WHEEL
tidesurf-0.2.1.dist-info/entry_points.txt
tidesurf-0.2.1.dist-info/top_level.txt
tidesurf-0.2.1.dist-info/RECORD
tidesurf-0.2.1.dist-info/licenses/LICENSE
