Metadata-Version: 2.4
Name: tidesurf
Version: 0.2.1
Summary: Tool for IDentification and Enumeration of Spliced and Unspliced Read Fragments.
Author: Jan T. Schleicher
Author-email: jan.schleicher@uni-tuebingen.de
License: GPL-3.0 license
Project-URL: Repository, https://github.com/janschleicher/tidesurf
Keywords: scRNA-seq,quantification,splicing,velocity
Classifier: Development Status :: 3 - Alpha
Classifier: Intended Audience :: Science/Research
Classifier: License :: OSI Approved :: GNU General Public License v3 (GPLv3)
Classifier: Programming Language :: Python :: 3.10
Classifier: Programming Language :: Python :: 3.11
Classifier: Programming Language :: Python :: 3.12
Classifier: Programming Language :: Python :: 3.13
Classifier: Topic :: Scientific/Engineering :: Bio-Informatics
Classifier: Operating System :: MacOS
Classifier: Operating System :: Unix
Requires-Python: >=3.10
License-File: LICENSE
Requires-Dist: cython
Requires-Dist: numpy
Requires-Dist: polars
Requires-Dist: scipy
Requires-Dist: anndata
Requires-Dist: pysam
Requires-Dist: tqdm
Provides-Extra: dev
Requires-Dist: ruff; extra == "dev"
Requires-Dist: pytest; extra == "dev"
Requires-Dist: pytest-cov; extra == "dev"
Provides-Extra: doc
Requires-Dist: sphinx; extra == "doc"
Requires-Dist: sphinx-book-theme; extra == "doc"
Requires-Dist: sphinx-copybutton; extra == "doc"
Requires-Dist: sphinx-autoapi; extra == "doc"
Requires-Dist: scanpydoc; extra == "doc"
Dynamic: license-file
